[
  {
    "tool": [
      {
        "id": "df6b83d6-fd9e-4ec1-bcd9-f618392f0c3d",
        "name": "Tool A",
        "description": "A powerful tool for data analysis",
        "image": "https://example.com/tool1.jpg",
        "created_at": "2023-07-31T11:58:13.781Z",
        "updated_at": "2023-08-01T05:38:30.160Z",
        "company_id": "main_entity_pk"
      },
      {
        "id": "64ca6820-e611-4fe1-93e6-e4831b9a7449",
        "name": "Tool B",
        "description": "An intuitive tool for project management",
        "image": "https://example.com/tool2.jpg",
        "created_at": "2023-07-31T21:55:04.950Z",
        "updated_at": "2023-07-31T14:50:19.991Z",
        "company_id": "main_entity_pk"
      },
      {
        "id": "cd50a63b-c99c-4910-80d0-178e87c69e42",
        "name": "Tool C",
        "description": "A versatile tool for graphic design",
        "image": "https://example.com/tool3.jpg",
        "created_at": "2023-07-31T18:55:43.781Z",
        "updated_at": "2023-07-31T13:29:21.350Z",
        "company_id": "main_entity_pk"
      },
      {
        "id": "2ffc9979-da9d-401c-866c-45931aa247cd",
        "name": "Tool D",
        "description": "A reliable tool for code debugging",
        "image": "https://example.com/tool4.jpg",
        "created_at": "2023-08-01T06:16:11.042Z",
        "updated_at": "2023-08-01T04:57:06.581Z",
        "company_id": "main_entity_pk"
      },
      {
        "id": "fd7b4d29-4fcb-4d35-80c2-83470c61764a",
        "name": "Tool E",
        "description": "An efficient tool for task automation",
        "image": "https://example.com/tool5.jpg",
        "created_at": "2023-07-31T20:00:40.475Z",
        "updated_at": "2023-07-31T17:24:30.661Z",
        "company_id": "main_entity_pk"
      }
    ],
    "rental": [
      {
        "id": "1e7cf276-7a5c-4f93-be2f-72f2ccd65acb",
        "start_date": "2023-08-01T01:50:11.005Z",
        "end_date": "2023-08-01T06:22:01.588Z",
        "created_at": "2023-08-01T03:27:36.200Z",
        "updated_at": "2023-07-31T12:11:59.778Z",
        "tool_id": "64ca6820-e611-4fe1-93e6-e4831b9a7449",
        "user_id": "user_entity_pk"
      },
      {
        "id": "dc90eab8-4ab4-4b9f-a4ea-2df53574fe94",
        "start_date": "2023-07-31T16:34:29.064Z",
        "end_date": "2023-07-31T17:45:03.322Z",
        "created_at": "2023-08-01T04:55:11.093Z",
        "updated_at": "2023-08-01T02:06:43.047Z",
        "tool_id": "64ca6820-e611-4fe1-93e6-e4831b9a7449",
        "user_id": "user_entity_pk"
      },
      {
        "id": "962c53b1-2a8f-46ee-9df4-9670ebc19e9f",
        "start_date": "2023-08-01T01:38:03.506Z",
        "end_date": "2023-08-01T01:12:44.931Z",
        "created_at": "2023-08-01T00:21:06.593Z",
        "updated_at": "2023-07-31T13:50:06.787Z",
        "tool_id": "cd50a63b-c99c-4910-80d0-178e87c69e42",
        "user_id": "user_entity_pk"
      },
      {
        "id": "dd7f8904-1c31-42e8-9cfb-460d5c8d9b6e",
        "start_date": "2023-07-31T10:03:38.606Z",
        "end_date": "2023-07-31T15:00:48.859Z",
        "created_at": "2023-08-01T06:35:04.317Z",
        "updated_at": "2023-08-01T04:58:11.159Z",
        "tool_id": "df6b83d6-fd9e-4ec1-bcd9-f618392f0c3d",
        "user_id": "user_entity_pk"
      },
      {
        "id": "2fe00a89-f8e2-46d3-abb8-be329709dd73",
        "start_date": "2023-07-31T15:23:30.223Z",
        "end_date": "2023-08-01T02:19:36.683Z",
        "created_at": "2023-08-01T05:32:35.616Z",
        "updated_at": "2023-07-31T15:02:59.923Z",
        "tool_id": "2ffc9979-da9d-401c-866c-45931aa247cd",
        "user_id": "user_entity_pk"
      }
    ]
  },
  {
    "tool": [
      {
        "id": "bea2fd96-bfbd-4bc5-8004-3c7e67f64074",
        "name": "Tool A",
        "description": "A powerful tool for data analysis",
        "image": "https://example.com/tool1.jpg",
        "created_at": "2023-07-31T19:48:35.774Z",
        "updated_at": "2023-07-31T10:24:00.906Z",
        "company_id": "main_entity_pk"
      },
      {
        "id": "23962035-919a-40e5-9d80-e03eb66f835e",
        "name": "Tool B",
        "description": "An intuitive tool for project management",
        "image": "https://example.com/tool2.jpg",
        "created_at": "2023-07-31T12:54:31.860Z",
        "updated_at": "2023-07-31T17:49:20.997Z",
        "company_id": "main_entity_pk"
      },
      {
        "id": "2d713bba-5c51-4d54-9775-71f34d83eb0f",
        "name": "Tool C",
        "description": "A versatile tool for graphic design",
        "image": "https://example.com/tool3.jpg",
        "created_at": "2023-07-31T23:07:18.300Z",
        "updated_at": "2023-07-31T18:33:04.341Z",
        "company_id": "main_entity_pk"
      },
      {
        "id": "b55d38fd-87c7-4bfa-b1e1-5abfbb4e3ece",
        "name": "Tool D",
        "description": "A reliable tool for code debugging",
        "image": "https://example.com/tool4.jpg",
        "created_at": "2023-07-31T21:25:00.298Z",
        "updated_at": "2023-08-01T03:51:05.522Z",
        "company_id": "main_entity_pk"
      },
      {
        "id": "205bd24b-fdc8-4343-aa92-6220575c0ec5",
        "name": "Tool E",
        "description": "An efficient tool for task automation",
        "image": "https://example.com/tool5.jpg",
        "created_at": "2023-07-31T16:16:32.761Z",
        "updated_at": "2023-07-31T16:31:29.204Z",
        "company_id": "main_entity_pk"
      }
    ],
    "rental": [
      {
        "id": "90bf3eb4-0053-4a84-9e38-2e68bb989092",
        "start_date": "2023-07-31T23:24:39.762Z",
        "end_date": "2023-07-31T14:11:53.897Z",
        "created_at": "2023-07-31T22:38:06.577Z",
        "updated_at": "2023-07-31T20:38:15.312Z",
        "tool_id": "b55d38fd-87c7-4bfa-b1e1-5abfbb4e3ece",
        "user_id": "user_entity_pk"
      },
      {
        "id": "621fc94b-776d-48eb-a0ce-82802bd325ee",
        "start_date": "2023-07-31T21:02:42.421Z",
        "end_date": "2023-07-31T20:45:46.776Z",
        "created_at": "2023-07-31T22:15:02.801Z",
        "updated_at": "2023-08-01T02:44:04.407Z",
        "tool_id": "23962035-919a-40e5-9d80-e03eb66f835e",
        "user_id": "user_entity_pk"
      },
      {
        "id": "25ada568-d121-469f-a750-28d90e0d2900",
        "start_date": "2023-07-31T15:16:06.123Z",
        "end_date": "2023-07-31T13:01:54.496Z",
        "created_at": "2023-08-01T00:34:28.073Z",
        "updated_at": "2023-08-01T07:17:48.734Z",
        "tool_id": "b55d38fd-87c7-4bfa-b1e1-5abfbb4e3ece",
        "user_id": "user_entity_pk"
      },
      {
        "id": "2598c7da-287f-4edf-a0eb-c6400257b4ad",
        "start_date": "2023-07-31T21:27:15.326Z",
        "end_date": "2023-07-31T23:42:17.671Z",
        "created_at": "2023-08-01T07:41:58.688Z",
        "updated_at": "2023-08-01T08:40:34.537Z",
        "tool_id": "205bd24b-fdc8-4343-aa92-6220575c0ec5",
        "user_id": "user_entity_pk"
      },
      {
        "id": "0015eb44-b6d9-4c91-8045-f9cd39bd6056",
        "start_date": "2023-08-01T08:06:35.827Z",
        "end_date": "2023-08-01T07:50:23.546Z",
        "created_at": "2023-08-01T03:11:09.913Z",
        "updated_at": "2023-07-31T14:55:06.446Z",
        "tool_id": "2d713bba-5c51-4d54-9775-71f34d83eb0f",
        "user_id": "user_entity_pk"
      }
    ]
  },
  {
    "tool": [
      {
        "id": "2d9e2cea-5c83-48b7-bddc-651e14f5a921",
        "name": "Tool A",
        "description": "A powerful tool for data analysis",
        "image": "https://example.com/tool1.jpg",
        "created_at": "2023-08-01T03:51:58.881Z",
        "updated_at": "2023-07-31T15:51:14.716Z",
        "company_id": "main_entity_pk"
      },
      {
        "id": "f8ce2c8b-c40d-4bbc-8c54-bbfc9b63e7c3",
        "name": "Tool B",
        "description": "An intuitive tool for project management",
        "image": "https://example.com/tool2.jpg",
        "created_at": "2023-08-01T00:50:36.850Z",
        "updated_at": "2023-07-31T13:35:13.970Z",
        "company_id": "main_entity_pk"
      },
      {
        "id": "270ac9b0-a206-41c4-8d69-cde54c7e889a",
        "name": "Tool C",
        "description": "A versatile tool for graphic design",
        "image": "https://example.com/tool3.jpg",
        "created_at": "2023-07-31T16:08:53.574Z",
        "updated_at": "2023-08-01T07:27:48.935Z",
        "company_id": "main_entity_pk"
      },
      {
        "id": "28f82b7c-2f76-494b-bec4-087fd5bdfb08",
        "name": "Tool D",
        "description": "A reliable tool for code debugging",
        "image": "https://example.com/tool4.jpg",
        "created_at": "2023-07-31T15:08:05.938Z",
        "updated_at": "2023-07-31T14:51:14.316Z",
        "company_id": "main_entity_pk"
      },
      {
        "id": "1cc47ecd-12c6-4347-a077-be67bcd8acd1",
        "name": "Tool E",
        "description": "An efficient tool for task automation",
        "image": "https://example.com/tool5.jpg",
        "created_at": "2023-07-31T18:49:58.361Z",
        "updated_at": "2023-07-31T20:23:02.228Z",
        "company_id": "main_entity_pk"
      }
    ],
    "rental": [
      {
        "id": "257a47fd-3a5d-4eaf-aae8-9538f58ac281",
        "start_date": "2023-07-31T17:00:31.459Z",
        "end_date": "2023-07-31T15:05:34.999Z",
        "created_at": "2023-07-31T17:53:56.450Z",
        "updated_at": "2023-08-01T07:38:23.818Z",
        "tool_id": "270ac9b0-a206-41c4-8d69-cde54c7e889a",
        "user_id": "user_entity_pk"
      },
      {
        "id": "2670fc82-addf-481a-b9a8-ac28d37e3a84",
        "start_date": "2023-07-31T17:37:56.982Z",
        "end_date": "2023-07-31T12:47:01.916Z",
        "created_at": "2023-08-01T08:28:44.959Z",
        "updated_at": "2023-07-31T10:10:03.021Z",
        "tool_id": "f8ce2c8b-c40d-4bbc-8c54-bbfc9b63e7c3",
        "user_id": "user_entity_pk"
      },
      {
        "id": "bc002f6d-95b9-4b5b-8c36-efe9ae2ccbf2",
        "start_date": "2023-07-31T23:48:14.776Z",
        "end_date": "2023-07-31T20:09:10.813Z",
        "created_at": "2023-07-31T15:34:54.265Z",
        "updated_at": "2023-07-31T19:31:02.111Z",
        "tool_id": "270ac9b0-a206-41c4-8d69-cde54c7e889a",
        "user_id": "user_entity_pk"
      },
      {
        "id": "1db5ec36-113b-42b5-875e-3b2bad3fc76c",
        "start_date": "2023-08-01T01:03:11.901Z",
        "end_date": "2023-07-31T16:11:41.411Z",
        "created_at": "2023-08-01T01:22:26.559Z",
        "updated_at": "2023-07-31T14:17:49.408Z",
        "tool_id": "28f82b7c-2f76-494b-bec4-087fd5bdfb08",
        "user_id": "user_entity_pk"
      },
      {
        "id": "429fdaf1-40b9-4b3b-8a0f-e332c265fed5",
        "start_date": "2023-08-01T03:59:40.129Z",
        "end_date": "2023-08-01T07:31:48.794Z",
        "created_at": "2023-07-31T15:02:17.586Z",
        "updated_at": "2023-07-31T23:42:13.092Z",
        "tool_id": "28f82b7c-2f76-494b-bec4-087fd5bdfb08",
        "user_id": "user_entity_pk"
      }
    ]
  },
  {
    "tool": [
      {
        "id": "d0e4800a-9c91-4ed3-a769-8d4348989414",
        "name": "Tool A",
        "description": "A powerful tool for data analysis",
        "image": "https://example.com/tool1.jpg",
        "created_at": "2023-07-31T18:53:51.080Z",
        "updated_at": "2023-08-01T05:54:44.216Z",
        "company_id": "main_entity_pk"
      },
      {
        "id": "094d34b9-d6d9-4384-bbd0-1be6ff754feb",
        "name": "Tool B",
        "description": "An intuitive tool for project management",
        "image": "https://example.com/tool2.jpg",
        "created_at": "2023-07-31T15:55:07.256Z",
        "updated_at": "2023-07-31T11:19:17.916Z",
        "company_id": "main_entity_pk"
      },
      {
        "id": "218c0c63-f0bf-44e1-acca-63bb603a2ad7",
        "name": "Tool C",
        "description": "A versatile tool for graphic design",
        "image": "https://example.com/tool3.jpg",
        "created_at": "2023-08-01T01:06:54.908Z",
        "updated_at": "2023-08-01T05:12:18.969Z",
        "company_id": "main_entity_pk"
      },
      {
        "id": "57d1503a-fd5c-4d72-ac32-f4716cbd685c",
        "name": "Tool D",
        "description": "A reliable tool for code debugging",
        "image": "https://example.com/tool4.jpg",
        "created_at": "2023-07-31T22:39:43.919Z",
        "updated_at": "2023-07-31T21:58:47.720Z",
        "company_id": "main_entity_pk"
      },
      {
        "id": "a780c379-0ae2-44d5-905f-20c8455aba38",
        "name": "Tool E",
        "description": "An efficient tool for task automation",
        "image": "https://example.com/tool5.jpg",
        "created_at": "2023-07-31T15:24:27.175Z",
        "updated_at": "2023-07-31T16:04:16.946Z",
        "company_id": "main_entity_pk"
      }
    ],
    "rental": [
      {
        "id": "a41b5da1-cc7a-4b5d-aca2-6c94c062e3ca",
        "start_date": "2023-08-01T03:45:29.765Z",
        "end_date": "2023-07-31T21:58:31.078Z",
        "created_at": "2023-08-01T04:45:24.236Z",
        "updated_at": "2023-07-31T22:08:49.053Z",
        "tool_id": "d0e4800a-9c91-4ed3-a769-8d4348989414",
        "user_id": "user_entity_pk"
      },
      {
        "id": "f24e18bf-5e17-4d97-b0a3-213fa076af3a",
        "start_date": "2023-08-01T03:45:52.110Z",
        "end_date": "2023-07-31T12:39:18.156Z",
        "created_at": "2023-08-01T04:36:34.396Z",
        "updated_at": "2023-07-31T17:24:55.449Z",
        "tool_id": "218c0c63-f0bf-44e1-acca-63bb603a2ad7",
        "user_id": "user_entity_pk"
      },
      {
        "id": "acff7d90-f18e-48e8-9e11-d76e7ea6771c",
        "start_date": "2023-07-31T15:29:52.292Z",
        "end_date": "2023-07-31T18:30:29.555Z",
        "created_at": "2023-07-31T20:55:40.850Z",
        "updated_at": "2023-07-31T18:39:50.064Z",
        "tool_id": "218c0c63-f0bf-44e1-acca-63bb603a2ad7",
        "user_id": "user_entity_pk"
      },
      {
        "id": "9a903e91-f6b8-43c3-8cfd-cdaa69a12cae",
        "start_date": "2023-08-01T00:14:26.265Z",
        "end_date": "2023-07-31T21:48:40.485Z",
        "created_at": "2023-07-31T22:16:22.095Z",
        "updated_at": "2023-07-31T17:23:24.832Z",
        "tool_id": "218c0c63-f0bf-44e1-acca-63bb603a2ad7",
        "user_id": "user_entity_pk"
      },
      {
        "id": "ec910861-bceb-4944-9718-dc888c12ee0b",
        "start_date": "2023-08-01T07:44:49.208Z",
        "end_date": "2023-07-31T16:21:56.180Z",
        "created_at": "2023-08-01T00:19:00.364Z",
        "updated_at": "2023-07-31T19:17:00.008Z",
        "tool_id": "57d1503a-fd5c-4d72-ac32-f4716cbd685c",
        "user_id": "user_entity_pk"
      }
    ]
  },
  {
    "tool": [
      {
        "id": "61df2800-c74b-442a-a972-48a0f5d124a7",
        "name": "Tool A",
        "description": "A powerful tool for data analysis",
        "image": "https://example.com/tool1.jpg",
        "created_at": "2023-08-01T05:53:28.221Z",
        "updated_at": "2023-07-31T16:32:28.891Z",
        "company_id": "main_entity_pk"
      },
      {
        "id": "52fc9f00-3261-4550-834b-ab5c687a5482",
        "name": "Tool B",
        "description": "An intuitive tool for project management",
        "image": "https://example.com/tool2.jpg",
        "created_at": "2023-07-31T19:53:27.787Z",
        "updated_at": "2023-07-31T11:23:58.881Z",
        "company_id": "main_entity_pk"
      },
      {
        "id": "842420e7-7c5f-47a5-9fc9-b549bf5c4112",
        "name": "Tool C",
        "description": "A versatile tool for graphic design",
        "image": "https://example.com/tool3.jpg",
        "created_at": "2023-08-01T07:32:16.493Z",
        "updated_at": "2023-07-31T20:22:12.987Z",
        "company_id": "main_entity_pk"
      },
      {
        "id": "beabae05-4e17-4e13-a1cc-233ef97a9863",
        "name": "Tool D",
        "description": "A reliable tool for code debugging",
        "image": "https://example.com/tool4.jpg",
        "created_at": "2023-07-31T23:51:26.224Z",
        "updated_at": "2023-07-31T10:32:32.599Z",
        "company_id": "main_entity_pk"
      },
      {
        "id": "1311612d-52a7-4a44-b5e8-e57dc522f86c",
        "name": "Tool E",
        "description": "An efficient tool for task automation",
        "image": "https://example.com/tool5.jpg",
        "created_at": "2023-07-31T17:05:07.571Z",
        "updated_at": "2023-07-31T15:55:45.292Z",
        "company_id": "main_entity_pk"
      }
    ],
    "rental": [
      {
        "id": "f98afb0c-30fc-4952-876c-91408a514b97",
        "start_date": "2023-07-31T18:15:42.271Z",
        "end_date": "2023-07-31T21:32:47.141Z",
        "created_at": "2023-08-01T07:24:53.111Z",
        "updated_at": "2023-07-31T15:19:08.954Z",
        "tool_id": "1311612d-52a7-4a44-b5e8-e57dc522f86c",
        "user_id": "user_entity_pk"
      },
      {
        "id": "4c20085d-6a00-44e1-a9aa-32cd1528ee95",
        "start_date": "2023-07-31T12:27:02.546Z",
        "end_date": "2023-08-01T08:53:57.373Z",
        "created_at": "2023-07-31T20:07:40.290Z",
        "updated_at": "2023-08-01T09:19:11.895Z",
        "tool_id": "61df2800-c74b-442a-a972-48a0f5d124a7",
        "user_id": "user_entity_pk"
      },
      {
        "id": "2cd42db5-4d3a-42d6-be1d-4eb6cfc9dfb8",
        "start_date": "2023-07-31T22:43:52.381Z",
        "end_date": "2023-08-01T01:52:09.754Z",
        "created_at": "2023-08-01T03:09:49.103Z",
        "updated_at": "2023-07-31T22:09:35.708Z",
        "tool_id": "1311612d-52a7-4a44-b5e8-e57dc522f86c",
        "user_id": "user_entity_pk"
      },
      {
        "id": "cb87a131-b18a-42c1-9b0b-fb6a7997e2d6",
        "start_date": "2023-08-01T01:16:55.603Z",
        "end_date": "2023-07-31T12:00:26.975Z",
        "created_at": "2023-07-31T10:26:31.514Z",
        "updated_at": "2023-07-31T17:34:23.103Z",
        "tool_id": "61df2800-c74b-442a-a972-48a0f5d124a7",
        "user_id": "user_entity_pk"
      },
      {
        "id": "98a1c8ad-a99f-4362-b1b3-49e57ef37468",
        "start_date": "2023-07-31T12:26:55.767Z",
        "end_date": "2023-08-01T08:16:17.681Z",
        "created_at": "2023-08-01T02:27:22.894Z",
        "updated_at": "2023-07-31T10:17:17.470Z",
        "tool_id": "61df2800-c74b-442a-a972-48a0f5d124a7",
        "user_id": "user_entity_pk"
      }
    ]
  },
  {
    "tool": [
      {
        "id": "dd4ab1d0-9434-456b-a967-f488d7c58565",
        "name": "Tool A",
        "description": "A powerful tool for data analysis",
        "image": "https://example.com/tool1.jpg",
        "created_at": "2023-07-31T10:46:09.340Z",
        "updated_at": "2023-07-31T12:23:50.696Z",
        "company_id": "main_entity_pk"
      },
      {
        "id": "356aeffe-e741-416c-852e-bc603d1b0401",
        "name": "Tool B",
        "description": "An intuitive tool for project management",
        "image": "https://example.com/tool2.jpg",
        "created_at": "2023-07-31T21:06:18.493Z",
        "updated_at": "2023-08-01T07:06:08.740Z",
        "company_id": "main_entity_pk"
      },
      {
        "id": "6a896ae8-f303-40fc-b7a6-604c2305e6f8",
        "name": "Tool C",
        "description": "A versatile tool for graphic design",
        "image": "https://example.com/tool3.jpg",
        "created_at": "2023-07-31T12:38:53.803Z",
        "updated_at": "2023-08-01T04:59:27.644Z",
        "company_id": "main_entity_pk"
      },
      {
        "id": "5378ac71-35f9-4602-b9ab-34b2326c80cc",
        "name": "Tool D",
        "description": "A reliable tool for code debugging",
        "image": "https://example.com/tool4.jpg",
        "created_at": "2023-08-01T01:11:37.073Z",
        "updated_at": "2023-07-31T13:15:09.763Z",
        "company_id": "main_entity_pk"
      },
      {
        "id": "0b98cb89-a319-4c28-a65c-03c360b1b642",
        "name": "Tool E",
        "description": "An efficient tool for task automation",
        "image": "https://example.com/tool5.jpg",
        "created_at": "2023-07-31T10:01:42.554Z",
        "updated_at": "2023-07-31T12:31:06.764Z",
        "company_id": "main_entity_pk"
      }
    ],
    "rental": [
      {
        "id": "31ba6a8f-2f54-4e12-9cc1-a92fa7dfcb8e",
        "start_date": "2023-07-31T21:46:58.569Z",
        "end_date": "2023-08-01T04:17:39.031Z",
        "created_at": "2023-07-31T09:50:27.518Z",
        "updated_at": "2023-08-01T08:16:26.705Z",
        "tool_id": "6a896ae8-f303-40fc-b7a6-604c2305e6f8",
        "user_id": "user_entity_pk"
      },
      {
        "id": "08f86e66-ba8b-4d44-870a-c0638f4f4e39",
        "start_date": "2023-07-31T21:58:33.522Z",
        "end_date": "2023-07-31T16:05:12.570Z",
        "created_at": "2023-07-31T17:56:46.311Z",
        "updated_at": "2023-08-01T06:42:29.150Z",
        "tool_id": "5378ac71-35f9-4602-b9ab-34b2326c80cc",
        "user_id": "user_entity_pk"
      },
      {
        "id": "0a6f1796-5db4-4405-97ab-de759bee4564",
        "start_date": "2023-07-31T21:23:38.166Z",
        "end_date": "2023-07-31T13:10:25.106Z",
        "created_at": "2023-07-31T11:59:14.498Z",
        "updated_at": "2023-08-01T05:46:59.688Z",
        "tool_id": "356aeffe-e741-416c-852e-bc603d1b0401",
        "user_id": "user_entity_pk"
      },
      {
        "id": "19ced0ba-984e-4161-8b10-6e646362a4de",
        "start_date": "2023-07-31T21:21:35.958Z",
        "end_date": "2023-07-31T23:06:12.514Z",
        "created_at": "2023-08-01T00:02:56.182Z",
        "updated_at": "2023-08-01T05:45:24.251Z",
        "tool_id": "5378ac71-35f9-4602-b9ab-34b2326c80cc",
        "user_id": "user_entity_pk"
      },
      {
        "id": "c0821273-8439-43a6-8000-f85d6442938a",
        "start_date": "2023-08-01T02:25:55.117Z",
        "end_date": "2023-07-31T18:59:38.660Z",
        "created_at": "2023-08-01T02:32:24.395Z",
        "updated_at": "2023-07-31T19:33:51.942Z",
        "tool_id": "356aeffe-e741-416c-852e-bc603d1b0401",
        "user_id": "user_entity_pk"
      }
    ]
  },
  {
    "tool": [
      {
        "id": "386b4cf5-8757-44a9-9db1-be32a18bbe74",
        "name": "Tool A",
        "description": "A powerful tool for data analysis",
        "image": "https://example.com/tool1.jpg",
        "created_at": "2023-07-31T16:13:18.131Z",
        "updated_at": "2023-07-31T18:45:25.763Z",
        "company_id": "main_entity_pk"
      },
      {
        "id": "83992c79-a646-4170-9490-868be882f52e",
        "name": "Tool B",
        "description": "An intuitive tool for project management",
        "image": "https://example.com/tool2.jpg",
        "created_at": "2023-08-01T04:14:44.368Z",
        "updated_at": "2023-08-01T01:47:28.638Z",
        "company_id": "main_entity_pk"
      },
      {
        "id": "79db6422-20a8-42e7-ad01-f64522ce5f00",
        "name": "Tool C",
        "description": "A versatile tool for graphic design",
        "image": "https://example.com/tool3.jpg",
        "created_at": "2023-08-01T00:50:31.746Z",
        "updated_at": "2023-07-31T14:26:27.269Z",
        "company_id": "main_entity_pk"
      },
      {
        "id": "fc3dbc7a-dcbf-40f5-ab57-f13f1bf441d6",
        "name": "Tool D",
        "description": "A reliable tool for code debugging",
        "image": "https://example.com/tool4.jpg",
        "created_at": "2023-08-01T07:22:41.472Z",
        "updated_at": "2023-08-01T06:39:59.390Z",
        "company_id": "main_entity_pk"
      },
      {
        "id": "e25181d2-0b14-48e9-ba90-6b35122d3062",
        "name": "Tool E",
        "description": "An efficient tool for task automation",
        "image": "https://example.com/tool5.jpg",
        "created_at": "2023-07-31T09:35:09.792Z",
        "updated_at": "2023-07-31T10:14:03.555Z",
        "company_id": "main_entity_pk"
      }
    ],
    "rental": [
      {
        "id": "361ac5a3-6a00-461a-98de-8886ae65db14",
        "start_date": "2023-08-01T04:17:48.946Z",
        "end_date": "2023-07-31T12:40:46.214Z",
        "created_at": "2023-07-31T22:41:12.436Z",
        "updated_at": "2023-08-01T02:55:39.499Z",
        "tool_id": "83992c79-a646-4170-9490-868be882f52e",
        "user_id": "user_entity_pk"
      },
      {
        "id": "86dc297b-124b-457f-a0c1-f64444198a6e",
        "start_date": "2023-08-01T03:37:05.924Z",
        "end_date": "2023-07-31T20:58:28.289Z",
        "created_at": "2023-07-31T13:08:52.290Z",
        "updated_at": "2023-08-01T07:35:56.407Z",
        "tool_id": "83992c79-a646-4170-9490-868be882f52e",
        "user_id": "user_entity_pk"
      },
      {
        "id": "cc180f2f-2573-4bd8-91c3-741981d84ce1",
        "start_date": "2023-07-31T11:11:56.469Z",
        "end_date": "2023-07-31T17:11:03.548Z",
        "created_at": "2023-07-31T19:23:40.323Z",
        "updated_at": "2023-07-31T13:39:39.138Z",
        "tool_id": "83992c79-a646-4170-9490-868be882f52e",
        "user_id": "user_entity_pk"
      },
      {
        "id": "3c7d6250-140f-4b58-a07a-d247ab4e9d91",
        "start_date": "2023-07-31T18:13:05.420Z",
        "end_date": "2023-07-31T20:06:49.456Z",
        "created_at": "2023-07-31T09:51:17.788Z",
        "updated_at": "2023-07-31T18:18:11.261Z",
        "tool_id": "79db6422-20a8-42e7-ad01-f64522ce5f00",
        "user_id": "user_entity_pk"
      },
      {
        "id": "2ca2a83c-8632-4574-8d32-83fa0cc58d71",
        "start_date": "2023-07-31T21:47:18.118Z",
        "end_date": "2023-07-31T13:08:52.456Z",
        "created_at": "2023-07-31T09:24:29.744Z",
        "updated_at": "2023-08-01T06:10:16.752Z",
        "tool_id": "83992c79-a646-4170-9490-868be882f52e",
        "user_id": "user_entity_pk"
      }
    ]
  },
  {
    "tool": [
      {
        "id": "384b4937-7c27-41a0-be6f-2e89604cf767",
        "name": "Tool A",
        "description": "A powerful tool for data analysis",
        "image": "https://example.com/tool1.jpg",
        "created_at": "2023-08-01T05:12:34.494Z",
        "updated_at": "2023-08-01T02:25:58.523Z",
        "company_id": "main_entity_pk"
      },
      {
        "id": "d5ff7ae2-5556-4ef7-8ba1-cc824d013232",
        "name": "Tool B",
        "description": "An intuitive tool for project management",
        "image": "https://example.com/tool2.jpg",
        "created_at": "2023-07-31T14:41:05.066Z",
        "updated_at": "2023-07-31T11:45:08.914Z",
        "company_id": "main_entity_pk"
      },
      {
        "id": "a099fe3a-a56b-4962-94e2-6ff74ed3c04b",
        "name": "Tool C",
        "description": "A versatile tool for graphic design",
        "image": "https://example.com/tool3.jpg",
        "created_at": "2023-07-31T11:17:51.673Z",
        "updated_at": "2023-08-01T01:39:00.607Z",
        "company_id": "main_entity_pk"
      },
      {
        "id": "287a8ced-db9a-4409-9225-90c255fa3de9",
        "name": "Tool D",
        "description": "A reliable tool for code debugging",
        "image": "https://example.com/tool4.jpg",
        "created_at": "2023-07-31T17:16:56.542Z",
        "updated_at": "2023-08-01T01:56:43.049Z",
        "company_id": "main_entity_pk"
      },
      {
        "id": "fe96e87d-663f-4dba-8b2c-a3ca326d2f74",
        "name": "Tool E",
        "description": "An efficient tool for task automation",
        "image": "https://example.com/tool5.jpg",
        "created_at": "2023-08-01T04:38:46.853Z",
        "updated_at": "2023-08-01T00:38:51.693Z",
        "company_id": "main_entity_pk"
      }
    ],
    "rental": [
      {
        "id": "f774def7-71fe-42d0-aac2-37d52f722c52",
        "start_date": "2023-07-31T20:03:31.619Z",
        "end_date": "2023-07-31T17:07:06.387Z",
        "created_at": "2023-07-31T23:56:35.085Z",
        "updated_at": "2023-07-31T22:59:37.444Z",
        "tool_id": "a099fe3a-a56b-4962-94e2-6ff74ed3c04b",
        "user_id": "user_entity_pk"
      },
      {
        "id": "86015aec-01e9-4849-883d-34ff1cb5dd1d",
        "start_date": "2023-08-01T03:13:07.151Z",
        "end_date": "2023-08-01T03:08:15.133Z",
        "created_at": "2023-07-31T14:55:56.205Z",
        "updated_at": "2023-07-31T19:21:16.203Z",
        "tool_id": "d5ff7ae2-5556-4ef7-8ba1-cc824d013232",
        "user_id": "user_entity_pk"
      },
      {
        "id": "0025b0f0-c430-401a-858b-433fae16dae1",
        "start_date": "2023-07-31T11:29:14.494Z",
        "end_date": "2023-07-31T21:34:37.206Z",
        "created_at": "2023-08-01T06:42:05.524Z",
        "updated_at": "2023-08-01T00:06:00.178Z",
        "tool_id": "384b4937-7c27-41a0-be6f-2e89604cf767",
        "user_id": "user_entity_pk"
      },
      {
        "id": "476224aa-6c53-47d1-b8f3-ac35356f66a6",
        "start_date": "2023-07-31T23:37:56.458Z",
        "end_date": "2023-07-31T19:09:25.423Z",
        "created_at": "2023-07-31T14:01:48.238Z",
        "updated_at": "2023-08-01T01:07:11.405Z",
        "tool_id": "fe96e87d-663f-4dba-8b2c-a3ca326d2f74",
        "user_id": "user_entity_pk"
      },
      {
        "id": "49950ff1-de9a-428c-844a-0bd03ac3ee5c",
        "start_date": "2023-08-01T06:08:18.775Z",
        "end_date": "2023-08-01T02:40:57.173Z",
        "created_at": "2023-07-31T10:41:30.796Z",
        "updated_at": "2023-07-31T10:38:49.496Z",
        "tool_id": "d5ff7ae2-5556-4ef7-8ba1-cc824d013232",
        "user_id": "user_entity_pk"
      }
    ]
  },
  {
    "tool": [
      {
        "id": "6e96eca5-80b9-4153-9d18-fe0755c8e4c1",
        "name": "Tool A",
        "description": "A powerful tool for data analysis",
        "image": "https://example.com/tool1.jpg",
        "created_at": "2023-08-01T06:19:06.471Z",
        "updated_at": "2023-07-31T15:19:09.797Z",
        "company_id": "main_entity_pk"
      },
      {
        "id": "1b437c9c-6d7a-4255-9744-f74a59800596",
        "name": "Tool B",
        "description": "An intuitive tool for project management",
        "image": "https://example.com/tool2.jpg",
        "created_at": "2023-07-31T13:56:40.616Z",
        "updated_at": "2023-08-01T06:35:24.820Z",
        "company_id": "main_entity_pk"
      },
      {
        "id": "f3d67903-3736-4df2-a675-cfb94d33a15b",
        "name": "Tool C",
        "description": "A versatile tool for graphic design",
        "image": "https://example.com/tool3.jpg",
        "created_at": "2023-07-31T15:14:37.604Z",
        "updated_at": "2023-08-01T02:54:13.616Z",
        "company_id": "main_entity_pk"
      },
      {
        "id": "fe1cc6f1-cd57-42f3-be66-420d26951f12",
        "name": "Tool D",
        "description": "A reliable tool for code debugging",
        "image": "https://example.com/tool4.jpg",
        "created_at": "2023-07-31T11:18:20.186Z",
        "updated_at": "2023-08-01T05:24:45.377Z",
        "company_id": "main_entity_pk"
      },
      {
        "id": "6af2d95a-b50b-4654-b8fb-f50aa76e78f8",
        "name": "Tool E",
        "description": "An efficient tool for task automation",
        "image": "https://example.com/tool5.jpg",
        "created_at": "2023-07-31T19:28:11.134Z",
        "updated_at": "2023-08-01T08:18:46.019Z",
        "company_id": "main_entity_pk"
      }
    ],
    "rental": [
      {
        "id": "c77909e2-2a36-46b3-8ebc-8645c2640666",
        "start_date": "2023-08-01T02:01:28.514Z",
        "end_date": "2023-07-31T19:18:20.137Z",
        "created_at": "2023-07-31T15:15:23.429Z",
        "updated_at": "2023-07-31T15:28:08.470Z",
        "tool_id": "1b437c9c-6d7a-4255-9744-f74a59800596",
        "user_id": "user_entity_pk"
      },
      {
        "id": "f47e45de-3e00-4e3b-bde7-31a0dd35ca97",
        "start_date": "2023-07-31T13:20:43.275Z",
        "end_date": "2023-08-01T07:52:10.781Z",
        "created_at": "2023-08-01T08:20:39.376Z",
        "updated_at": "2023-07-31T19:08:59.966Z",
        "tool_id": "6af2d95a-b50b-4654-b8fb-f50aa76e78f8",
        "user_id": "user_entity_pk"
      },
      {
        "id": "f5bbd6b1-9ac0-43db-a6b1-fa948db901a2",
        "start_date": "2023-07-31T23:32:10.323Z",
        "end_date": "2023-08-01T05:21:47.951Z",
        "created_at": "2023-08-01T08:36:57.359Z",
        "updated_at": "2023-07-31T11:37:57.552Z",
        "tool_id": "6af2d95a-b50b-4654-b8fb-f50aa76e78f8",
        "user_id": "user_entity_pk"
      },
      {
        "id": "fa209ee9-26ae-4623-a282-d9e8ae1bb502",
        "start_date": "2023-07-31T18:28:01.410Z",
        "end_date": "2023-07-31T11:11:00.482Z",
        "created_at": "2023-07-31T14:26:48.997Z",
        "updated_at": "2023-07-31T23:45:00.299Z",
        "tool_id": "fe1cc6f1-cd57-42f3-be66-420d26951f12",
        "user_id": "user_entity_pk"
      },
      {
        "id": "3c943e36-1222-4283-95d9-dedbf7486709",
        "start_date": "2023-08-01T05:13:48.825Z",
        "end_date": "2023-08-01T05:45:46.913Z",
        "created_at": "2023-08-01T02:36:50.800Z",
        "updated_at": "2023-07-31T22:17:43.617Z",
        "tool_id": "1b437c9c-6d7a-4255-9744-f74a59800596",
        "user_id": "user_entity_pk"
      }
    ]
  },
  {
    "tool": [
      {
        "id": "68525f93-3a3b-4810-ae5c-cadd7656a36a",
        "name": "Tool A",
        "description": "A powerful tool for data analysis",
        "image": "https://example.com/tool1.jpg",
        "created_at": "2023-08-01T03:54:51.096Z",
        "updated_at": "2023-07-31T16:01:44.882Z",
        "company_id": "main_entity_pk"
      },
      {
        "id": "868df8e2-2436-4e49-91de-a33fb34967a0",
        "name": "Tool B",
        "description": "An intuitive tool for project management",
        "image": "https://example.com/tool2.jpg",
        "created_at": "2023-07-31T14:17:51.169Z",
        "updated_at": "2023-07-31T11:13:18.761Z",
        "company_id": "main_entity_pk"
      },
      {
        "id": "8cda74ef-d8c8-4e69-9de9-b4e748f4e253",
        "name": "Tool C",
        "description": "A versatile tool for graphic design",
        "image": "https://example.com/tool3.jpg",
        "created_at": "2023-08-01T06:42:33.755Z",
        "updated_at": "2023-07-31T20:40:09.067Z",
        "company_id": "main_entity_pk"
      },
      {
        "id": "124f45d7-2e64-43f1-baff-e21f042087f1",
        "name": "Tool D",
        "description": "A reliable tool for code debugging",
        "image": "https://example.com/tool4.jpg",
        "created_at": "2023-08-01T02:39:45.631Z",
        "updated_at": "2023-07-31T16:16:21.380Z",
        "company_id": "main_entity_pk"
      },
      {
        "id": "a1614731-aed4-4b4b-9c5d-fa9bdaa7c65a",
        "name": "Tool E",
        "description": "An efficient tool for task automation",
        "image": "https://example.com/tool5.jpg",
        "created_at": "2023-07-31T10:46:34.415Z",
        "updated_at": "2023-08-01T05:24:26.350Z",
        "company_id": "main_entity_pk"
      }
    ],
    "rental": [
      {
        "id": "95ed368e-195a-4a2e-94df-4cda2d261412",
        "start_date": "2023-07-31T10:06:54.267Z",
        "end_date": "2023-07-31T20:36:51.107Z",
        "created_at": "2023-07-31T22:48:04.162Z",
        "updated_at": "2023-08-01T02:30:49.329Z",
        "tool_id": "8cda74ef-d8c8-4e69-9de9-b4e748f4e253",
        "user_id": "user_entity_pk"
      },
      {
        "id": "14a5c91e-78f4-4681-82c6-207235d36a53",
        "start_date": "2023-07-31T23:56:11.910Z",
        "end_date": "2023-07-31T10:09:40.633Z",
        "created_at": "2023-08-01T02:42:31.798Z",
        "updated_at": "2023-07-31T15:42:27.070Z",
        "tool_id": "124f45d7-2e64-43f1-baff-e21f042087f1",
        "user_id": "user_entity_pk"
      },
      {
        "id": "57ea582e-6ba3-4f55-a9e5-ea2d99544703",
        "start_date": "2023-08-01T04:46:23.678Z",
        "end_date": "2023-07-31T09:36:19.355Z",
        "created_at": "2023-07-31T12:41:30.863Z",
        "updated_at": "2023-07-31T13:07:09.262Z",
        "tool_id": "8cda74ef-d8c8-4e69-9de9-b4e748f4e253",
        "user_id": "user_entity_pk"
      },
      {
        "id": "f3fb14c3-06e1-4a40-94db-4304fd9cecb4",
        "start_date": "2023-07-31T21:46:43.482Z",
        "end_date": "2023-07-31T11:10:56.121Z",
        "created_at": "2023-07-31T21:09:28.464Z",
        "updated_at": "2023-07-31T14:33:02.573Z",
        "tool_id": "868df8e2-2436-4e49-91de-a33fb34967a0",
        "user_id": "user_entity_pk"
      },
      {
        "id": "8a0afa3f-6e7b-43fe-823c-949fc5605bc7",
        "start_date": "2023-07-31T18:30:39.260Z",
        "end_date": "2023-07-31T22:02:59.907Z",
        "created_at": "2023-08-01T07:58:32.817Z",
        "updated_at": "2023-07-31T17:11:53.517Z",
        "tool_id": "a1614731-aed4-4b4b-9c5d-fa9bdaa7c65a",
        "user_id": "user_entity_pk"
      }
    ]
  }
]
